bump2v/__main__.py
bump2v/test.ipynb
bump2v-1.1.9.dist-info/LICENSE
bump2v-1.1.9.dist-info/METADATA
bump2v-1.1.9.dist-info/WHEEL
bump2v-1.1.9.dist-info/entry_points.txt
bump2v-1.1.9.dist-info/top_level.txt
bump2v-1.1.9.dist-info/RECORD
