Metadata-Version: 2.1
Name: bump2v
Version: 1.1.9
Summary: This is a package to bump version numbers in a project. Fully automated versioning. Prefer to bump2version package instructions.
License: MIT License
Project-URL: Homepage, https://github.com/maimul/bump2v
Keywords: alternative,version,versioning,bump2version,automate,python,deployment,devops,dev,ops,automation,bump,versioning
Classifier: Programming Language :: Python :: 3
Classifier: License :: OSI Approved :: MIT License
Classifier: Operating System :: OS Independent
License-File: LICENSE
Requires-Dist: bump2version==1.0.1
